hallucounter/__init__.py
hallucounter/detector.py
hallucounter/nli_scores.py
hallucounter-1.0.0.dist-info/METADATA
hallucounter-1.0.0.dist-info/WHEEL
hallucounter-1.0.0.dist-info/top_level.txt
hallucounter-1.0.0.dist-info/RECORD
