Metadata-Version: 2.2
Name: hallucounter
Version: 1.0.0
Summary: A tool for reference-free hallucination detection in LLM-generated responses
Classifier: Programming Language :: Python :: 3
Classifier: License :: OSI Approved :: MIT License
Classifier: Operating System :: OS Independent
Requires-Python: >=3.9
Requires-Dist: numpy==1.26.4
Requires-Dist: scikit-learn==1.3.2
Dynamic: classifier
Dynamic: description
Dynamic: description-content-type
Dynamic: requires-dist
Dynamic: requires-python
Dynamic: summary
